Metadata-Version: 2.1
Name: keybert-base-chinese
Version: 0.0.3
Summary: 基于keybert提取中文文本关键词
Home-page: https://pypi.org/user/May.xiaoya.zhang/
Author: may.xiaoya.zhang
Author-email: may.xiaoya.zhang@gmail.com
License: UNKNOWN
Platform: UNKNOWN
